pytak/__init__.py
pytak/classes.py
pytak/client_functions.py
pytak/commands.py
pytak/constants.py
pytak/crypto_functions.py
pytak/functions.py
pytak/asyncio_dgram/LICENSE
pytak/asyncio_dgram/__init__.py
pytak/asyncio_dgram/aio.py
pytak-7.1.0.dist-info/LICENSE
pytak-7.1.0.dist-info/METADATA
pytak-7.1.0.dist-info/WHEEL
pytak-7.1.0.dist-info/top_level.txt
pytak-7.1.0.dist-info/RECORD
